{
  "project_info": {
    "project_number": "2814632136",
    "project_id": "ghl-india-assets",
    "storage_bucket": "ghl-india-assets.firebasestorage.app"
  },
  "client": [
    {
      "client_info": {
        "mobilesdk_app_id": "1:2814632136:android:10439c90fc21246d4e85fd",
        "android_client_info": {
          "package_name": "com.ghl.app"
        }
      },
      "oauth_client": [],
      "api_key": [
        {
          "current_key": "AIzaSyAmK7Nv3PKDf5AKuXoEccPBPRLrnspivvE"
        }
      ],
      "services": {
        "appinvite_service": {
          "other_platform_oauth_client": []
        }
      }
    }
  ],
  "configuration_version": "1"
}